{
  "free_type": {
    "loading_progress": {
      "font_file_name": "kgdx_noto_sans_mono_bold",
      "font_size": 32.0,
      "default_characters": false,
      "characters": "%0123456789",
      "name": "loading_progress",
      "extension": "ttf",
      "file_type": "internal",
      "preload": false
    }
  },
  "json": {
    "body_def": {
      "class": "dev.ebnbin.insaniquarium.body.BodyDefJsonWrapper",
      "name": "body_def",
      "extension": "json",
      "file_type": "internal",
      "preload": true
    }
  },
  "texture": {
    "amp": {
      "region": {
        "row": 5,
        "column": 2,
        "animation": {
          "duration": 0.5,
          "mode": "loop"
        }
      },
      "stretchable": null,
      "name": "amp",
      "extension": "png",
      "file_type": "local",
      "preload": false
    },
    "angie": {
      "region": {
        "row": 2,
        "column": 5,
        "animation": {
          "duration": 0.5,
          "mode": "loop"
        }
      },
      "stretchable": null,
      "name": "angie",
      "extension": "png",
      "file_type": "local",
      "preload": false
    },
    "aquarium_a": {
      "region": null,
      "stretchable": {
        "x": [
          0,
          160,
          1120,
          160
        ],
        "y": [
          0,
          80,
          680,
          40
        ]
      },
      "name": "aquarium_a",
      "extension": "png",
      "file_type": "local",
      "preload": false
    },
    "aquarium_b": {
      "region": null,
      "stretchable": {
        "x": [
          0,
          160,
          1120,
          160
        ],
        "y": [
          0,
          80,
          680,
          40
        ]
      },
      "name": "aquarium_b",
      "extension": "png",
      "file_type": "local",
      "preload": false
    },
    "aquarium_c": {
      "region": null,
      "stretchable": {
        "x": [
          0,
          160,
          1120,
          160
        ],
        "y": [
          0,
          80,
          680,
          40
        ]
      },
      "name": "aquarium_c",
      "extension": "png",
      "file_type": "local",
      "preload": false
    },
    "aquarium_d": {
      "region": null,
      "stretchable": {
        "x": [
          0,
          160,
          1120,
          160
        ],
        "y": [
          0,
          80,
          680,
          40
        ]
      },
      "name": "aquarium_d",
      "extension": "png",
      "file_type": "local",
      "preload": false
    },
    "aquarium_e": {
      "region": null,
      "stretchable": {
        "x": [
          0,
          160,
          1120,
          160
        ],
        "y": [
          0,
          80,
          680,
          40
        ]
      },
      "name": "aquarium_e",
      "extension": "png",
      "file_type": "local",
      "preload": false
    },
    "aquarium_f": {
      "region": null,
      "stretchable": {
        "x": [
          0,
          160,
          1120,
          160
        ],
        "y": [
          0,
          80,
          680,
          40
        ]
      },
      "name": "aquarium_f",
      "extension": "png",
      "file_type": "local",
      "preload": false
    },
    "blip": {
      "region": {
        "row": 2,
        "column": 5,
        "animation": {
          "duration": 0.5,
          "mode": "loop"
        }
      },
      "stretchable": null,
      "name": "blip",
      "extension": "png",
      "file_type": "local",
      "preload": false
    },
    "brinkley": {
      "region": {
        "row": 2,
        "column": 5,
        "animation": {
          "duration": 1.0,
          "mode": "loop"
        }
      },
      "stretchable": null,
      "name": "brinkley",
      "extension": "png",
      "file_type": "local",
      "preload": false
    },
    "clyde": {
      "region": {
        "row": 2,
        "column": 5,
        "animation": {
          "duration": 1.0,
          "mode": "loop"
        }
      },
      "stretchable": null,
      "name": "clyde",
      "extension": "png",
      "file_type": "local",
      "preload": false
    },
    "gash": {
      "region": {
        "row": 2,
        "column": 5,
        "animation": {
          "duration": 0.5,
          "mode": "loop"
        }
      },
      "stretchable": null,
      "name": "gash",
      "extension": "png",
      "file_type": "local",
      "preload": false
    },
    "gumbo": {
      "region": {
        "row": 2,
        "column": 5,
        "animation": {
          "duration": 0.5,
          "mode": "loop"
        }
      },
      "stretchable": null,
      "name": "gumbo",
      "extension": "png",
      "file_type": "local",
      "preload": false
    },
    "itchy": {
      "region": {
        "row": 2,
        "column": 5,
        "animation": {
          "duration": 0.5,
          "mode": "loop"
        }
      },
      "stretchable": null,
      "name": "itchy",
      "extension": "png",
      "file_type": "local",
      "preload": false
    },
    "loading_background": {
      "region": null,
      "stretchable": {
        "x": [
          0,
          1,
          1279,
          1
        ],
        "y": [
          0,
          2,
          719,
          1
        ]
      },
      "name": "loading_background",
      "extension": "png",
      "file_type": "local",
      "preload": false
    },
    "meryl": {
      "region": {
        "row": 2,
        "column": 5,
        "animation": {
          "duration": 0.5,
          "mode": "loop"
        }
      },
      "stretchable": null,
      "name": "meryl",
      "extension": "png",
      "file_type": "local",
      "preload": false
    },
    "niko": {
      "region": {
        "row": 2,
        "column": 5,
        "animation": {
          "duration": 0.5,
          "mode": "loop_pingpong"
        }
      },
      "stretchable": null,
      "name": "niko",
      "extension": "png",
      "file_type": "local",
      "preload": false
    },
    "nimbus": {
      "region": {
        "row": 2,
        "column": 5,
        "animation": {
          "duration": 0.5,
          "mode": "loop"
        }
      },
      "stretchable": null,
      "name": "nimbus",
      "extension": "png",
      "file_type": "local",
      "preload": false
    },
    "nostradamus": {
      "region": {
        "row": 2,
        "column": 5,
        "animation": {
          "duration": 0.5,
          "mode": "loop"
        }
      },
      "stretchable": null,
      "name": "nostradamus",
      "extension": "png",
      "file_type": "local",
      "preload": false
    },
    "prego": {
      "region": {
        "row": 2,
        "column": 5,
        "animation": {
          "duration": 0.5,
          "mode": "loop"
        }
      },
      "stretchable": null,
      "name": "prego",
      "extension": "png",
      "file_type": "local",
      "preload": false
    },
    "presto": {
      "region": {
        "row": 2,
        "column": 5,
        "animation": {
          "duration": 0.5,
          "mode": "loop"
        }
      },
      "stretchable": null,
      "name": "presto",
      "extension": "png",
      "file_type": "local",
      "preload": false
    },
    "rhubarb": {
      "region": {
        "row": 2,
        "column": 5,
        "animation": {
          "duration": 1.0,
          "mode": "loop"
        }
      },
      "stretchable": null,
      "name": "rhubarb",
      "extension": "png",
      "file_type": "local",
      "preload": false
    },
    "rufus": {
      "region": {
        "row": 2,
        "column": 5,
        "animation": {
          "duration": 0.5,
          "mode": "loop"
        }
      },
      "stretchable": null,
      "name": "rufus",
      "extension": "png",
      "file_type": "local",
      "preload": false
    },
    "seymour": {
      "region": {
        "row": 2,
        "column": 5,
        "animation": {
          "duration": 1.0,
          "mode": "loop"
        }
      },
      "stretchable": null,
      "name": "seymour",
      "extension": "png",
      "file_type": "local",
      "preload": false
    },
    "shrapnel": {
      "region": {
        "row": 2,
        "column": 5,
        "animation": {
          "duration": 1.0,
          "mode": "loop"
        }
      },
      "stretchable": null,
      "name": "shrapnel",
      "extension": "png",
      "file_type": "local",
      "preload": false
    },
    "stanley": {
      "region": {
        "row": 2,
        "column": 5,
        "animation": {
          "duration": 0.5,
          "mode": "loop"
        }
      },
      "stretchable": null,
      "name": "stanley",
      "extension": "png",
      "file_type": "local",
      "preload": false
    },
    "stinky": {
      "region": {
        "row": 2,
        "column": 5,
        "animation": {
          "duration": 0.5,
          "mode": "loop"
        }
      },
      "stretchable": null,
      "name": "stinky",
      "extension": "png",
      "file_type": "local",
      "preload": false
    },
    "vert": {
      "region": {
        "row": 2,
        "column": 5,
        "animation": {
          "duration": 0.5,
          "mode": "loop_pingpong"
        }
      },
      "stretchable": null,
      "name": "vert",
      "extension": "png",
      "file_type": "local",
      "preload": false
    },
    "wadsworth": {
      "region": {
        "row": 2,
        "column": 5,
        "animation": {
          "duration": 0.5,
          "mode": "loop"
        }
      },
      "stretchable": null,
      "name": "wadsworth",
      "extension": "png",
      "file_type": "local",
      "preload": false
    },
    "walter": {
      "region": {
        "row": 2,
        "column": 5,
        "animation": {
          "duration": 0.5,
          "mode": "loop_pingpong"
        }
      },
      "stretchable": null,
      "name": "walter",
      "extension": "png",
      "file_type": "local",
      "preload": false
    },
    "zorf": {
      "region": {
        "row": 2,
        "column": 5,
        "animation": {
          "duration": 0.5,
          "mode": "loop"
        }
      },
      "stretchable": null,
      "name": "zorf",
      "extension": "png",
      "file_type": "local",
      "preload": false
    }
  }
}